text2speech/__about__.py
text2speech/__init__.py
text2speech/answer_to_speech.py
text2speech/document_to_speech.py
text2speech/errors.py
text2speech/utils/__init__.py
text2speech/utils/text_to_speech.py
farm_haystack_text2speech-1.1.1.dist-info/METADATA
farm_haystack_text2speech-1.1.1.dist-info/WHEEL
farm_haystack_text2speech-1.1.1.dist-info/licenses/LICENSE.txt
farm_haystack_text2speech-1.1.1.dist-info/RECORD
